{
  "title": "Onur Senture",
  "description": "I'm Onur, a multidisciplinary designer based in Ankara and co-founder of <a href=\"https://web.archive.org/web/20230710045931/https://orkestra.co/\" target=\"_blank\">Orkestra Studios</a>. <a href=\"https://cs.bilkent.edu.tr\" target=\"_blank\">Bilkent CS</a> alumnus.",
  "author": "Onur Senture",
  "email": "hello@onursenture.com",
  "url": "https://onursenture.com",
  "social": {
    "x": "w00f",
    "dribbble": "onursenture",
    "github": "onursenture",
    "goodreads": "onur",
    "letterboxd": "onur",
    "instapaper": "w00f"
  }
}
